chinese_calendar/__init__.py
chinese_calendar/constants.py
chinese_calendar/solar_terms.py
chinese_calendar/utils.py
chinesecalendar-1.11.0.dist-info/METADATA
chinesecalendar-1.11.0.dist-info/WHEEL
chinesecalendar-1.11.0.dist-info/top_level.txt
chinesecalendar-1.11.0.dist-info/RECORD
